[
    {
        "key": "/github",
        "value": "https://github.com/Hexstream"
    },
    {
        "key": "/linkedin",
        "value": "https://www.linkedin.com/in/hexstream"
    },
    {
        "key": "/keybase",
        "value": "https://keybase.io/hexstream"
    },
    {
        "key": "/discord",
        "value": "https://abc.hexstream.xyz/#discord"
    },
    {
        "key": "/telegram",
        "value": "https://t.me/Hexstream"
    },
    {
        "key": "/reddit",
        "value": "https://www.reddit.com/user/Loginwallmenot/"
    },
    {
        "key": "/launchpad",
        "value": "https://bugs.launchpad.net/~hexstream"
    },
    {
        "key": "/cliki",
        "value": "https://cliki.net/Jean-Philippe%20Paradis"
    },
    {
        "key": "/x",
        "value": "https://x.com/HexstreamSoft"
    },
    {
        "key": "/hacker-news",
        "value": "https://news.ycombinator.com/user?id=Hexstream"
    },
    {
        "key": "/coderwall",
        "value": "https://coderwall.com/Hexstream"
    },
    {
        "key": "/lobsters",
        "value": "https://lobste.rs/u/Hexstream"
    },
    {
        "key": "/clhs",
        "value": "https://www.lispworks.com/documentation/HyperSpec/Front/index.htm"
    },
    {
        "key": "/format",
        "value": "https://www.hexstreamsoft.com/articles/common-lisp-format-reference/clhs-summary/#subsections-summary-table"
    },
    {
        "key": "/keyboard",
        "value": "https://status-quo.hexstream.expert/hardware/planck-ez/#my-config"
    },
    {
        "key": "/inkbunny",
        "value": "https://inkbunny.net/Hexstream"
    },
    {
        "key": "/youtube",
        "value": "https://www.youtube.com/@Hexstream"
    },
    {
        "key": "/e621",
        "value": "https://e621.net/users/hexstream"
    },
    {
        "key": "/deviantart",
        "value": "https://www.deviantart.com/hexstream"
    },
    {
        "key": "/furaffinity",
        "value": "https://www.furaffinity.net/user/hexstream/"
    },
    {
        "key": "/derpibooru",
        "value": "https://derpibooru.org/profiles/Hexstream"
    },
    {
        "key": "/oc",
        "value": "https://ponies.hexstream.net/images/#hexstream_pony-town"
    },
    {
        "key": "/values",
        "value": "https://workshop.hexstream.xyz/svg/originals/hexstream-hierarchy-of-awesomeness.svg"
    }
]
